LICENSE
MANIFEST.in
README.md
setup.py
mqhandler/__init__.py
mqhandler/fasta_grepper.py
mqhandler/filter_ids.py
mqhandler/intersection_analysis.py
mqhandler/map_orthologs.py
mqhandler/reduce_genenames.py
mqhandler/remap_genenames.py
mqhandler.egg-info/PKG-INFO
mqhandler.egg-info/SOURCES.txt
mqhandler.egg-info/dependency_links.txt
mqhandler.egg-info/requires.txt
mqhandler.egg-info/top_level.txt
mqhandler/mq_utils/HGNC_mapping.py
mqhandler/mq_utils/__init__.py
mqhandler/mq_utils/logger.py
mqhandler/mq_utils/mapping_handler.py
mqhandler/mq_utils/plotting.py
mqhandler/mq_utils/runner_utils.py