Metadata-Version: 2.1
Name: mqhandler
Version: 0.0.29
Summary: Collection of scripts to transform and remap MaxQuant output files
Home-page: http://pypi.python.org/pypi/mqhandler/
Author: Klaudia Adamowicz
Author-email: klaudia.adamowicz@uni-hamburg.de
License: LICENSE
Classifier: Programming Language :: Python :: 3.7
Classifier: Programming Language :: Python :: 3.8
Classifier: Programming Language :: Python :: 3.9
Classifier: Intended Audience :: Science/Research
Requires-Python: >=3.7
License-File: LICENSE
